geode_hybridremesh/__init__.py
geode_hybridremesh/brep.py
geode_hybridremesh/geode_hybridremesh_py_brep.cpython-39-x86_64-linux-gnu.so
geode_hybridremesh/libGeode-HybridRemesh_brep.so
Geode_HybridRemesh-1.1.4.dist-info/METADATA
Geode_HybridRemesh-1.1.4.dist-info/WHEEL
Geode_HybridRemesh-1.1.4.dist-info/top_level.txt
Geode_HybridRemesh-1.1.4.dist-info/RECORD
