Metadata-Version: 2.1
Name: Geode-HybridRemesh
Version: 1.1.4
Summary: Hybrid remeshing Geode-solutions OpenGeode module
Home-page: https://github.com/Geode-solutions/Geode-HybridRemesh
Author: Geode-solutions
Author-email: contact@geode-solutions.com
License: Proprietary
